cincan/__init__.py
cincan/__main__.py
cincan/command_inspector.py
cincan/command_log.py
cincan/configuration.py
cincan/container_check.py
cincan/file_tool.py
cincan/frontend.py
cincan/image_fetcher.py
cincan/tar_tool.py
cincan/utils.py
cincan/version_handler.py
cincan_command-0.2.12.dist-info/LICENSE
cincan_command-0.2.12.dist-info/METADATA
cincan_command-0.2.12.dist-info/WHEEL
cincan_command-0.2.12.dist-info/entry_points.txt
cincan_command-0.2.12.dist-info/top_level.txt
cincan_command-0.2.12.dist-info/RECORD
