Metadata-Version: 2.1
Name: cincan-command
Version: 0.2.12
Summary: Cincan wrapper for dockerized command-line tools
Home-page: https://gitlab.com/cincan/cincan-command
Author: Rauli Kaksonen
Author-email: rauli.kaksonen@gmail.com
License: UNKNOWN
Platform: UNKNOWN
Classifier: Programming Language :: Python :: 3
Classifier: License :: OSI Approved :: MIT License
Classifier: Operating System :: OS Independent
Requires-Python: >=3.6
Requires-Dist: docker (>=4.3.0)
Requires-Dist: cincan-registry (>=0.2.0)
